{"Version":"1.0.0.0","LastState":11,"Modules":[{"ValidatedSteerId":8,"ValidatedDriveId":7,"ValidatedEncoderId":9,"IsEncoderOffsetConfigured":true,"IsDeviceSelectionCompleted":true,"IsConfigurationCompleted":true,"ModuleName":"Front Left","ModuleId":0,"Encoder":{"Id":9,"Name":"frontLeft","Model":"CANCoder","CANbus":"DD433A91394C485320202050180718FF","CANbusFriendly":"Canivore"},"SteerMotor":{"Id":8,"Name":"frontLeftSteer","Model":"Talon FX vers. C","CANbus":"DD433A91394C485320202050180718FF","CANbusFriendly":"Canivore"},"DriveMotor":{"Id":7,"Name":"frontLeftDrive","Model":"Talon FX vers. C","CANbus":"DD433A91394C485320202050180718FF","CANbusFriendly":"Canivore"},"IsSteerInverted":false,"EncoderOffset":-0.267333984375,"DriveMotorSelectionState":1,"SteerMotorSelectionState":1,"SteerEncoderSelectionState":1,"IsModuleValidationComplete":true},{"ValidatedSteerId":2,"ValidatedDriveId":1,"ValidatedEncoderId":12,"IsEncoderOffsetConfigured":true,"IsDeviceSelectionCompleted":true,"IsConfigurationCompleted":true,"ModuleName":"Front Right","ModuleId":1,"Encoder":{"Id":12,"Name":"frontRight","Model":"CANCoder","CANbus":"DD433A91394C485320202050180718FF","CANbusFriendly":"Canivore"},"SteerMotor":{"Id":2,"Name":"frontRightSteer","Model":"Talon FX vers. C","CANbus":"DD433A91394C485320202050180718FF","CANbusFriendly":"Canivore"},"DriveMotor":{"Id":1,"Name":"frontRightDrive","Model":"Talon FX vers. C","CANbus":"DD433A91394C485320202050180718FF","CANbusFriendly":"Canivore"},"IsSteerInverted":false,"EncoderOffset":-0.228515625,"DriveMotorSelectionState":1,"SteerMotorSelectionState":1,"SteerEncoderSelectionState":1,"IsModuleValidationComplete":true},{"ValidatedSteerId":6,"ValidatedDriveId":5,"ValidatedEncoderId":10,"IsEncoderOffsetConfigured":true,"IsDeviceSelectionCompleted":true,"IsConfigurationCompleted":true,"ModuleName":"Back Left","ModuleId":2,"Encoder":{"Id":10,"Name":"backLeft","Model":"CANCoder","CANbus":"DD433A91394C485320202050180718FF","CANbusFriendly":"Canivore"},"SteerMotor":{"Id":6,"Name":"backLeftSteer","Model":"Talon FX vers. C","CANbus":"DD433A91394C485320202050180718FF","CANbusFriendly":"Canivore"},"DriveMotor":{"Id":5,"Name":"backLeftDrive","Model":"Talon FX vers. C","CANbus":"DD433A91394C485320202050180718FF","CANbusFriendly":"Canivore"},"IsSteerInverted":false,"EncoderOffset":-0.91357421875,"DriveMotorSelectionState":1,"SteerMotorSelectionState":1,"SteerEncoderSelectionState":1,"IsModuleValidationComplete":true},{"ValidatedSteerId":4,"ValidatedDriveId":3,"ValidatedEncoderId":11,"IsEncoderOffsetConfigured":true,"IsDeviceSelectionCompleted":true,"IsConfigurationCompleted":true,"ModuleName":"Back Right","ModuleId":3,"Encoder":{"Id":11,"Name":"backRight","Model":"CANCoder","CANbus":"DD433A91394C485320202050180718FF","CANbusFriendly":"Canivore"},"SteerMotor":{"Id":4,"Name":"backRightSteer","Model":"Talon FX vers. C","CANbus":"DD433A91394C485320202050180718FF","CANbusFriendly":"Canivore"},"DriveMotor":{"Id":3,"Name":"backRightDrive","Model":"Talon FX vers. C","CANbus":"DD433A91394C485320202050180718FF","CANbusFriendly":"Canivore"},"IsSteerInverted":true,"EncoderOffset":-0.60107421875,"DriveMotorSelectionState":1,"SteerMotorSelectionState":1,"SteerEncoderSelectionState":1,"IsModuleValidationComplete":true}],"SwerveOptions":{"IsValidConfiguration":true,"Gyro":{"Id":20,"Name":"Pigeon 2 (Device ID 20)","Model":"Pigeon 2","CANbus":"DD433A91394C485320202050180718FF","CANbusFriendly":"Canivore"},"IsValidGyroCANbus":true,"VerticalTrackSizeInches":21.5,"HorizontalTrackSizeInches":23.0,"WheelRadiusInches":2.0,"IsLeftSideInverted":false,"IsRightSideInverted":true,"SwerveModuleType":-1,"SwerveModuleConfiguration":{"_CouplingRatio":0.0,"_CustomName":null,"SteerRatio":25.0,"Flipped":-1,"DriveRatio":5.142857,"CouplingRatio":0.0,"CustomName":null},"HasVerifiedSteer":true,"HasVerifiedDrive":true}}